README.md
setup.py
stGACN/ATAC_preprocess.py
stGACN/__init__.py
stGACN/analysis.py
stGACN/gat_conv_pyg.py
stGACN/model.py
stGACN/plot.py
stGACN/preprocess.py
stGACN/stGACN.py
stGACN/utils.py
stGACN.egg-info/PKG-INFO
stGACN.egg-info/SOURCES.txt
stGACN.egg-info/dependency_links.txt
stGACN.egg-info/top_level.txt