Metadata-Version: 2.1
Name: stGACN
Version: 0.1
Summary: add douyin effect to image
Home-page: https://github.com/Briskzxm/stGACN
Author: Xinming Zhang
Author-email: zhangxm9921@mails.jlu.edu.cn
Classifier: Programming Language :: Python :: 3
Classifier: License :: OSI Approved :: MIT License
Classifier: Operating System :: OS Independent
